vodesfunc/__init__.py
vodesfunc/denoise.py
vodesfunc/misc.py
vodesfunc/noise.py
vodesfunc/rescale.py
vodesfunc/scale.py
vodesfunc/spikefinder.py
vodesfunc/util.py
vodesfunc/rescale_ext/__init__.py
vodesfunc/rescale_ext/base.py
vodesfunc/rescale_ext/fieldbased_rescale.py
vodesfunc/rescale_ext/mixed_rescale.py
vodesfunc/rescale_ext/regular_rescale.py
vodesfunc-1.10.0.dist-info/METADATA
vodesfunc-1.10.0.dist-info/WHEEL
vodesfunc-1.10.0.dist-info/licenses/LICENSE
vodesfunc-1.10.0.dist-info/RECORD
