Metadata-Version: 2.4
Name: vodesfunc
Version: 1.10.0
Summary: Vodes' random Vapoursynth Functions.
Project-URL: Source Code, https://github.com/Vodes/vodesfunc
Project-URL: Contact, https://discord.gg/Kf94Nv6WVN
Author-email: Vodes <vodes.imp@gmail.com>
License-Expression: MPL-2.0
License-File: LICENSE
Classifier: Intended Audience :: Developers
Classifier: Intended Audience :: End Users/Desktop
Classifier: License :: OSI Approved :: Mozilla Public License 2.0 (MPL 2.0)
Classifier: Natural Language :: English
Classifier: Operating System :: OS Independent
Classifier: Programming Language :: Python :: 3.11
Classifier: Topic :: Multimedia :: Video
Classifier: Typing :: Typed
Requires-Python: >=3.11
Requires-Dist: jetpytools>=1.2.3
Requires-Dist: packaging>=23.2
Requires-Dist: vapoursynth>=66
Requires-Dist: vsjetpack>=0.5.3
Requires-Dist: vsmuxtools>=0.3.0
